numeros_primos/PRIMOS.py
NUMPRIMO-5.2.dist-info/LICENSE.txt
NUMPRIMO-5.2.dist-info/METADATA
NUMPRIMO-5.2.dist-info/WHEEL
NUMPRIMO-5.2.dist-info/top_level.txt
NUMPRIMO-5.2.dist-info/RECORD
